setup.py
shinkenplugins/__init__.py
shinkenplugins.plugins.toshiba_ups.egg-info/PKG-INFO
shinkenplugins.plugins.toshiba_ups.egg-info/SOURCES.txt
shinkenplugins.plugins.toshiba_ups.egg-info/dependency_links.txt
shinkenplugins.plugins.toshiba_ups.egg-info/entry_points.txt
shinkenplugins.plugins.toshiba_ups.egg-info/namespace_packages.txt
shinkenplugins.plugins.toshiba_ups.egg-info/requires.txt
shinkenplugins.plugins.toshiba_ups.egg-info/top_level.txt
shinkenplugins/plugins/__init__.py
shinkenplugins/plugins/toshiba_ups/__init__.py
shinkenplugins/plugins/toshiba_ups/toshiba_ups.py