Metadata-Version: 1.0
Name: shinkenplugins.plugins.toshiba-ups
Version: 1.2
Summary: Plugin to check Toshiba UPSs
Home-page: https://github.com/savoirfairelinux/sfl-shinken-plugins
Author: Thibault Cohen
Author-email: thibault.cohen@savoirfairelinux.com
License: GPL3+
Platform: any
